django_rtdb-1.2.0.dist-info/DESCRIPTION.rst
django_rtdb-1.2.0.dist-info/METADATA
django_rtdb-1.2.0.dist-info/RECORD
django_rtdb-1.2.0.dist-info/WHEEL
django_rtdb-1.2.0.dist-info/metadata.json
django_rtdb-1.2.0.dist-info/top_level.txt
rtdb/__init__.py
rtdb/admin.py
rtdb/apps.py
rtdb/models.py
rtdb/raw_models.py
rtdb/stats.py
