Metadata-Version: 2.0
Name: django-rtdb
Version: 1.2.0
Summary: Simplified access to the Request Tracker 4 database
Home-page: https://github.com/UNINETT/django-rtdb
Author: Hanne Moa
Author-email: hanne.moa@uninett.no
License: UNKNOWN
Platform: any
Classifier: Development Status :: 4 - Beta
Classifier: Environment :: Web Environment
Classifier: Framework :: Django
Classifier: Intended Audience :: Developers
Classifier: License :: OSI Approved :: MIT License
Classifier: Operating System :: OS Independent
Classifier: Programming Language :: Python :: 2.7
Classifier: Programming Language :: Python :: 3.4
Classifier: Programming Language :: Python :: 3.5
Classifier: Topic :: Software Development :: Libraries :: Application Frameworks
Classifier: Topic :: Software Development :: Libraries :: Python Modules
